birra/__init__.py
birra/birra.py
birra-0.1.1.dist-info/METADATA
birra-0.1.1.dist-info/WHEEL
birra-0.1.1.dist-info/RECORD
